LICENSE
README.md
geminitrack
setup.py
Agunua/__init__.py
Agunua/cli.py
Agunua/status.py
Agunua/urltinkering.py
Agunua/utils.py
Agunua/../CHANGES
Agunua/../LICENSE
Agunua/../agunua.md
Agunua/../geminitrack.md
Agunua/../sample-client.py
agunua.egg-info/PKG-INFO
agunua.egg-info/SOURCES.txt
agunua.egg-info/dependency_links.txt
agunua.egg-info/entry_points.txt
agunua.egg-info/requires.txt
agunua.egg-info/top_level.txt
tests/test_egsam.py
tests/test_full.py
tests/test_gemtext_parse.py
tests/test_invalid_uris.py
tests/test_iri.py
tests/test_network_longtime.py
tests/test_urlmerge.py
tests/test_utils.py