Metadata-Version: 2.1
Name: agunua
Version: 1.7.2
Summary: A library for the development of Gemini clients
Home-page: https://framagit.org/bortzmeyer/agunua/
Author: Stéphane Bortzmeyer
Author-email: stephane+framagit@bortzmeyer.org
License: GPL
Keywords: Gemini
Classifier: Development Status :: 5 - Production/Stable
Classifier: Programming Language :: Python :: 3
Classifier: License :: OSI Approved :: GNU General Public License v2 (GPLv2)
Classifier: Intended Audience :: Developers
Classifier: Topic :: Internet
Classifier: Operating System :: OS Independent
Requires-Python: >=3.7
License-File: LICENSE
